[
  {
    "entity_name": "#FFFFFF",
    "last_index": 69.1,
    "forecast_7d": [
      69.11,
      69.11,
      69.11,
      69.11,
      69.11,
      69.11,
      69.11
    ],
    "direction": "flat",
    "confidence": 0.007,
    "data_days": 26
  },
  {
    "entity_name": "新增經歷",
    "last_index": 58.6,
    "forecast_7d": [
      58.59,
      58.59,
      58.59,
      58.59,
      58.59,
      58.59,
      58.59
    ],
    "direction": "flat",
    "confidence": 0.0,
    "data_days": 26
  },
  {
    "entity_name": "#0000FF",
    "last_index": 54.3,
    "forecast_7d": [
      54.24,
      54.23,
      54.22,
      54.21,
      54.21,
      54.2,
      54.19
    ],
    "direction": "flat",
    "confidence": 0.049,
    "data_days": 26
  },
  {
    "entity_name": "#FFFF00",
    "last_index": 52.15,
    "forecast_7d": [
      52.13,
      52.13,
      52.12,
      52.12,
      52.12,
      52.12,
      52.11
    ],
    "direction": "flat",
    "confidence": 0.014,
    "data_days": 26
  },
  {
    "entity_name": "宿命白",
    "last_index": 39.85,
    "forecast_7d": [
      39.84,
      39.84,
      39.84,
      39.84,
      39.84,
      39.84,
      39.84
    ],
    "direction": "flat",
    "confidence": 0.0,
    "data_days": 26
  },
  {
    "entity_name": "大邦奶奶",
    "last_index": 39.85,
    "forecast_7d": [
      39.8,
      39.8,
      39.79,
      39.78,
      39.78,
      39.77,
      39.76
    ],
    "direction": "flat",
    "confidence": 0.06,
    "data_days": 26
  },
  {
    "entity_name": "紅色",
    "last_index": 39.7,
    "forecast_7d": [
      39.65,
      39.65,
      39.64,
      39.63,
      39.63,
      39.62,
      39.61
    ],
    "direction": "flat",
    "confidence": 0.051,
    "data_days": 26
  },
  {
    "entity_name": "#800080",
    "last_index": 37.5,
    "forecast_7d": [
      37.46,
      37.45,
      37.45,
      37.44,
      37.43,
      37.43,
      37.42
    ],
    "direction": "flat",
    "confidence": 0.038,
    "data_days": 26
  },
  {
    "entity_name": "#007500",
    "last_index": 19.95,
    "forecast_7d": [
      20.04,
      20.06,
      20.07,
      20.08,
      20.09,
      20.1,
      20.12
    ],
    "direction": "flat",
    "confidence": 0.075,
    "data_days": 26
  },
  {
    "entity_name": "#C90000",
    "last_index": 19.95,
    "forecast_7d": [
      19.94,
      19.94,
      19.94,
      19.94,
      19.94,
      19.94,
      19.94
    ],
    "direction": "flat",
    "confidence": 0.006,
    "data_days": 26
  }
]