{
  "generated_at": "2026-07-18T20:55:42Z",
  "market_temperature": 61.5,
  "market_temperature_v2": 61.5,
  "active_groups": 107,
  "formula_version": "v3-seo-discoverability",
  "data_coverage": {
    "instagram": 0.91,
    "x": 0.24,
    "threads": 0.0,
    "social_post_dates": 0.31,
    "seo_ready_profiles": 0.85,
    "audience_insights": 0.0,
    "commercial_insights": 0.0,
    "views": 0.0
  },
  "weekly_highlights": {
    "top_group": "幻獣",
    "social_king": "小嗨花花HimiKo",
    "social_focus": "小嗨花花HimiKo",
    "market_temperature": 61.5
  },
  "rising_stars": [
    "恋乃 もも",
    "いのり",
    "うみ",
    "優芽 Yuume",
    "夏川千晴"
  ],
  "heat_drop": [],
  "top_members": [
    "小嗨花花HimiKo",
    "瑠冥青璃",
    "小豆 Azuki",
    "六角のえり",
    "甘崎紗音",
    "姫宮まい",
    "伊波花怜",
    "Nya",
    "星野 さかな",
    "姫川乃愛"
  ]
}